starpoint/__init__.py
starpoint/_utils.py
starpoint/db.py
starpoint/embedding.py
starpoint/pandas.py
starpoint/reader.py
starpoint/writer.py
starpoint-0.7.0.dist-info/METADATA
starpoint-0.7.0.dist-info/WHEEL
starpoint-0.7.0.dist-info/licenses/LICENSE
starpoint-0.7.0.dist-info/RECORD
