Metadata-Version: 2.3
Name: starpoint
Version: 0.7.0
Summary: SDK for Starpoint DB
Project-URL: Homepage, https://github.com/starpoint-ai/sdk
Project-URL: Bug Tracker, https://github.com/starpoint-ai/sdk/issues
Author-email: pointable <package-maintainers@pointable.ai>
License-File: LICENSE
Classifier: License :: OSI Approved :: MIT License
Classifier: Operating System :: OS Independent
Classifier: Programming Language :: Python :: 3
Requires-Python: >=3.7
Requires-Dist: more-itertools<=10.1,>=8
Requires-Dist: pandas~=2.0
Requires-Dist: requests~=2.31
Requires-Dist: validators~=0.21
Provides-Extra: dev
Requires-Dist: pip-tools~=6.14; extra == 'dev'
Requires-Dist: pre-commit~=3.3; extra == 'dev'
Requires-Dist: pytest-cov~=4.1; extra == 'dev'
Requires-Dist: pytest~=7.3; extra == 'dev'
